parascope/__init__.py
parascope/_launcher.py
parascope-0.3.0.data/scripts/rparascope
parascope-0.3.0.dist-info/METADATA
parascope-0.3.0.dist-info/WHEEL
parascope-0.3.0.dist-info/entry_points.txt
parascope-0.3.0.dist-info/top_level.txt
parascope-0.3.0.dist-info/RECORD
