Metadata-Version: 2.4
Name: parascope
Version: 0.3.0
Summary: Weggli ruleset scanner for source code and binaries
Author-email: "Sam L. Thomas" <s@ghost.sh>
License-Expression: MIT
Project-URL: Homepage, https://xv.ax/parascope
Project-URL: Repository, https://github.com/xorpse/parascope
Keywords: ida,ida-pro,idalib,vulnerability,weggli
Classifier: Programming Language :: Rust
Classifier: Programming Language :: Python :: 3
Requires-Python: >=3.9
